LICENSE
README.md
setup.py
totality/__init__.py
totality/imports.py
totality/intertxt.py
totality/totality.py
totality.egg-info/PKG-INFO
totality.egg-info/SOURCES.txt
totality.egg-info/dependency_links.txt
totality.egg-info/requires.txt
totality.egg-info/top_level.txt
totality/corpora/__init__.py
totality/corpora/corpus.py
totality/database/__init__.py
totality/database/baseobj.py
totality/database/docspace.py
totality/database/relspace.py
totality/models/__init__.py
totality/models/matching.py
totality/models/models.py
totality/models/networks.py
totality/texts/__init__.py
totality/texts/text.py
totality/texts/textlist.py
totality/utils/__init__.py
totality/utils/downloads.py
totality/utils/io.py
totality/utils/logs.py
totality/utils/misc.py
totality/utils/utils.py